framework/__init__.py
framework/base_class.py
framework/conftest.py
framework/exceptions.py
framework/exit_code.py
framework/extract.py
framework/global_attribute.py
framework/http_client.py
framework/render_data.py
framework/report.py
framework/script.py
framework/startapp.py
framework/validate.py
framework/db/__init__.py
framework/db/mysql_db.py
framework/db/redis_db.py
framework/utils/__init__.py
framework/utils/common.py
framework/utils/date_util.py
framework/utils/encrypt.py
framework/utils/lark_util.py
framework/utils/log_util.py
framework/utils/mock_util.py
framework/utils/yaml_util.py
pytest_api_framework_alpha-0.3.18.dist-info/METADATA
pytest_api_framework_alpha-0.3.18.dist-info/WHEEL
pytest_api_framework_alpha-0.3.18.dist-info/top_level.txt
pytest_api_framework_alpha-0.3.18.dist-info/RECORD
