Metadata-Version: 2.4
Name: pytest-api-framework-alpha
Version: 0.3.18
Author: alpha
Author-email: 
Requires-Python: >=3.6
Requires-Dist: allure-pytest==2.13.1
Requires-Dist: allure-python-commons==2.13.1
Requires-Dist: cn2an==0.5.19
Requires-Dist: DBUtils==3.1.0
Requires-Dist: Faker==18.3.2
Requires-Dist: jsonpath==0.82
Requires-Dist: pytest==7.2.2
Requires-Dist: python-dotenv==1.0.1
Requires-Dist: PyYAML==6.0.1
Requires-Dist: python-box==7.2.0
Requires-Dist: pycryptodome==3.21.0
Requires-Dist: pyotp==2.9.0
Requires-Dist: pytest-order==1.3.0
Requires-Dist: PyMySQL==1.1.0
Requires-Dist: redis==3.5.3
Requires-Dist: requests==2.25.1
Requires-Dist: requests-toolbelt==1.0.0
Requires-Dist: retry==0.9.2
Requires-Dist: dill==0.3.8
Requires-Dist: simplejson==3.20.1
Dynamic: author
Dynamic: requires-dist
Dynamic: requires-python
